codesec/__init__.py
codesec/cdsc.py
codesec/config.ini
codesec-0.2.4.dist-info/entry_points.txt
codesec-0.2.4.dist-info/LICENSE
codesec-0.2.4.dist-info/WHEEL
codesec-0.2.4.dist-info/METADATA
codesec-0.2.4.dist-info/RECORD
