Metadata-Version: 2.1
Name: codesec
Version: 0.2.4
Summary: Generates code headers for your text files
Author-email: Raeed Ahmed <ruahmed7868@gmail.com>
Classifier: License :: OSI Approved :: GNU General Public License v3 or later (GPLv3+)
Requires-Dist: pyperclip
Project-URL: Changelog, https://github.com/RaeedAhmed/codesec/blob/main/CHANGELOG.md
Project-URL: Home, https://github.com/RaeedAhmed/codesec
